blossom/__init__.py
blossom/__main__.py
blossom/blossom.py
blossalg-1.1.0.dist-info/LICENSE
blossalg-1.1.0.dist-info/METADATA
blossalg-1.1.0.dist-info/WHEEL
blossalg-1.1.0.dist-info/entry_points.txt
blossalg-1.1.0.dist-info/top_level.txt
blossalg-1.1.0.dist-info/RECORD
