Metadata-Version: 2.1
Name: blossalg
Version: 1.1.0
Summary: Construct a maximum matching on a graph with the blossom algorithm
Home-page: https://github.com/nenb/blossalg
Author: Nick Byrne
License: MIT
Platform: UNKNOWN
Classifier: License :: OSI Approved :: MIT License
Classifier: Programming Language :: Python
Classifier: Programming Language :: Python :: 2.7
Classifier: Programming Language :: Python :: 3.8
Requires-Dist: future
